LICENSE
MANIFEST.in
README.rst
setup.py
name_tools/__init__.py
name_tools/affixes.py
name_tools/forms.py
name_tools/match.py
name_tools/split.py
name_tools.egg-info/PKG-INFO
name_tools.egg-info/SOURCES.txt
name_tools.egg-info/dependency_links.txt
name_tools.egg-info/top_level.txt