Metadata-Version: 1.1
Name: name-tools
Version: 0.1.7
Summary: Library for manipulating and comparing (English) names
Home-page: http://github.com/openstates/name_tools
Author: Michael Stephens
Author-email: me@mikej.st
License: BSD
Platform: any
Classifier: Development Status :: 4 - Beta
Classifier: Intended Audience :: Developers
Classifier: License :: OSI Approved :: BSD License
Classifier: Natural Language :: English
Classifier: Operating System :: OS Independent
Classifier: Programming Language :: Python
Classifier: Topic :: Text Processing :: Linguistic
